asts-0.9.10.dist-info/METADATA
asts-0.9.10.dist-info/top_level.txt
asts-0.9.10.dist-info/WHEEL
asts-0.9.10.dist-info/RECORD
asts/tree-sitter-typescript-typescript.so
asts/tree-sitter-css.so
asts/asts.py
asts/__init__.py
asts/tree-sitter-jsdoc.so
asts/types.py
asts/libffi.so.6.0.2
asts/tree-sitter-java.so
asts/tree-sitter-regex.so
asts/tree-sitter-go.so
asts/tree-sitter-json.so
asts/tree-sitter-typescript-tsx.so
asts/tree-sitter-bash.so
asts/tree-sitter-c.so
asts/tree-sitter-rust.so
asts/version.py
asts/libtree-sitter.so.0.0
asts/tree-sitter-javascript.so
asts/tree-sitter-python.so
asts/utility.py
asts/tree-sitter-html.so
asts/tree-sitter-interface
asts/tree-sitter-wrapper.so
asts/tree-sitter-cpp.so
