Metadata-Version: 2.1
Name: asts
Version: 0.9.10
Summary: A library for programmatic software modification
Home-page: https://github.com/grammatech/sel
Author: Eric Schulte and GrammaTech
License: GPLv3+
Project-URL: Bug Reports, https://github.com/grammatech/sel/issues
Project-URL: Source, https://github.com/grammatech/sel/
Keywords: software-engineering,source,program-synthesis
Classifier: Development Status :: 3 - Alpha
Classifier: Intended Audience :: Developers
Classifier: License :: OSI Approved :: GNU General Public License v3 or later (GPLv3+)
Classifier: Programming Language :: Python :: 3
Classifier: Programming Language :: Python :: 3.6
Classifier: Programming Language :: Python :: 3.7
Classifier: Programming Language :: Python :: 3.8
Classifier: Programming Language :: Python :: 3.9
Classifier: Programming Language :: Python :: 3.10
Requires-Python: >=3.6.0
Requires-Dist: backports.cached-property
Requires-Dist: typing-extensions
Requires-Dist: psutil
Requires-Dist: pygments
Provides-Extra: dev
Requires-Dist: black; extra == "dev"
Requires-Dist: flake8; extra == "dev"
Requires-Dist: md-toc; extra == "dev"
Requires-Dist: mypy; extra == "dev"
Requires-Dist: pre-commit; extra == "dev"
Requires-Dist: pyright; extra == "dev"
Requires-Dist: pytest; extra == "dev"
Requires-Dist: twine; extra == "dev"
Requires-Dist: types-setuptools; extra == "dev"
